sqlalchemy_builder/__init__.py
sqlalchemy_builder/_functional.py
sqlalchemy_builder/py.typed
sqlalchemy_builder/select.py
sqlalchemy_builder-0.1.1.dist-info/METADATA
sqlalchemy_builder-0.1.1.dist-info/WHEEL
sqlalchemy_builder-0.1.1.dist-info/licenses/LICENSE
sqlalchemy_builder-0.1.1.dist-info/RECORD
