Metadata-Version: 2.4
Name: sqlalchemy-builder
Version: 0.1.1
Summary: Build SQLAlchemy statements avoiding common footguns.
Project-URL: HomePage, https://github.com/Jamie-Chang/sqlalchemy-builder
Author-email: Jamie Chang <jamie.cheng.chang@gmail.com>
Maintainer-email: Jamie Chang <jamie.cheng.chang@gmail.com>
License:                                  Apache License
License-File: LICENSE
Classifier: Development Status :: 4 - Beta
Classifier: Programming Language :: Python
Classifier: Programming Language :: Python :: 3.9
Classifier: Programming Language :: Python :: 3.10
Classifier: Programming Language :: Python :: 3.11
Classifier: Programming Language :: Python :: 3.12
Classifier: Programming Language :: Python :: 3.13
Requires-Python: >=3.9
Requires-Dist: sqlalchemy>=2.0.0
Requires-Dist: typing-extensions>=4.12.2
